lyman/__init__.py
lyman/frontend.py
lyman/glm.py
lyman/signals.py
lyman/surface.py
lyman/utils.py
lyman/visualizations.py
lyman/tests/__init__.py
lyman/tests/test_frontend.py
lyman/tests/test_glm.py
lyman/tests/test_signals.py
lyman/tests/test_surface.py
lyman/tests/test_utils.py
lyman/tests/test_visualizations.py
lyman/workflows/__init__.py
lyman/workflows/model.py
lyman/workflows/preproc.py
lyman/workflows/template.py
lyman/workflows/tests/__init__.py
lyman/workflows/tests/test_model.py
lyman/workflows/tests/test_preproc.py
lyman/workflows/tests/test_template.py
lyman-2.0.0.data/scripts/lyman
lyman-2.0.0.dist-info/LICENSE
lyman-2.0.0.dist-info/METADATA
lyman-2.0.0.dist-info/WHEEL
lyman-2.0.0.dist-info/top_level.txt
lyman-2.0.0.dist-info/RECORD
