Metadata-Version: 2.1
Name: lyman
Version: 2.0.0
Summary: lyman: neuroimaging analysis in Python
Home-page: http://www.cns.nyu.edu/~mwaskom/software/lyman/
Maintainer: Michael Waskom
Maintainer-email: mwaskom@nyu.edu
License: BSD (3-clause)
Download-URL: https://github.com/mwaskom/lyman
Platform: UNKNOWN
Classifier: Intended Audience :: Science/Research
Classifier: Programming Language :: Python :: 3.7
Classifier: Programming Language :: Python :: 3.8
Classifier: License :: OSI Approved :: BSD License
Classifier: Operating System :: POSIX
Classifier: Operating System :: Unix
Classifier: Operating System :: MacOS
Requires-Python: >=3.7
Requires-Dist: numpy
Requires-Dist: scipy
Requires-Dist: pandas
Requires-Dist: matplotlib
Requires-Dist: pyyaml
Requires-Dist: traits
Requires-Dist: nibabel
Requires-Dist: nipype (>=1.0)
